Metadata-Version: 1.0
Name: gyin-distributions
Version: 1.0
Summary: Gaussian and Binomial distributions
Home-page: UNKNOWN
Author: Guopeng Yin
Author-email: yinguopeng@gmail.com
License: UNKNOWN
Platform: UNKNOWN
